diderypy/__init__.py
diderypy/app.py
diderypy/cli.py
diderypy/diderying.py
diderypy/core/__init__.py
diderypy/core/behaving.py
diderypy/flo/main.flo
diderypy/help/__init__.py
diderypy/help/consensing.py
diderypy/help/helping.py
diderypy/help/signing.py
diderypy/lib/__init__.py
diderypy/lib/didering.py
diderypy/lib/generating.py
diderypy/lib/history_eventing.py
diderypy/lib/historying.py
diderypy/lib/otping.py
diderypy/models/__init__.py
diderypy/models/consensing.py
diderypy/models/responding.py
diderypy-0.1.1.dist-info/METADATA
diderypy-0.1.1.dist-info/RECORD
diderypy-0.1.1.dist-info/WHEEL
diderypy-0.1.1.dist-info/entry_points.txt
diderypy-0.1.1.dist-info/top_level.txt
