Metadata-Version: 2.1
Name: diderypy
Version: 0.1.1
Summary: SDK for working with Didery servers
Home-page: https://github.com/reputage/didery.py
Author: Nicholas Telfer
Author-email: nick.telfer@consensys.net
License: Apache2
Platform: UNKNOWN
Classifier: Development Status :: 3 - Alpha
Classifier: Intended Audience :: Developers
Classifier: License :: OSI Approved :: Apache Software License
Classifier: Operating System :: Unix
Classifier: Operating System :: POSIX
Classifier: Programming Language :: Python
Classifier: Programming Language :: Python :: 3.6
Classifier: Programming Language :: Python :: Implementation :: CPython
Classifier: Topic :: Utilities
Requires-Dist: click
Requires-Dist: ioflo (>=1.6.8)
Requires-Dist: libnacl (>=1.5.1)
Requires-Dist: simplejson (>=3.11.1)
Requires-Dist: arrow (>=0.10.0)
Requires-Dist: pytest
